LICENSE.txt
MANIFEST.in
README.md
setup.cfg
setup.py
src/kobo/__init__.py
src/kobo/__main__.py
src/kobo/helper.py
src/kobo/parser.py
src/kobo/redirects.py
src/kobo/server.py
src/kobo/resources/content/index.md
src/kobo/resources/static/css/grid.css
src/kobo/resources/static/css/main.css
src/kobo/resources/templates/404.html
src/kobo/resources/templates/index-list.html
src/kobo/resources/templates/index.html
src/kobo/resources/templates/page.html
src/kobo_md.egg-info/PKG-INFO
src/kobo_md.egg-info/SOURCES.txt
src/kobo_md.egg-info/dependency_links.txt
src/kobo_md.egg-info/requires.txt
src/kobo_md.egg-info/top_level.txt