Metadata-Version: 2.1
Name: kobo-md
Version: 0.1.19
Summary: Markdown Compiler + Server
Home-page: https://github.com/dwLG00/kobo/
Author: Dylan Wallace
Requires-Python: >=3.8
License-File: LICENSE.txt
Requires-Dist: flask
Requires-Dist: bs4
Requires-Dist: markdown
Requires-Dist: markdown-katex
